mavspy/__init__.py
mavspy/mavs.py
mavspy/mavs_lib_loader.py
mavspy/data/actors/actors/l200_actor_top_loop.json
mavspy/data/actors/actors/lambo_actor_outer_loop.json
mavspy/data/environments/vicksburg_clear_midnight.json
mavspy/data/environments/vicksburg_clear_noon.json
mavspy/data/environments/vicksburg_hazy.json
mavspy/data/environments/vicksburg_raining.json
mavspy/data/environments/stardata/bsc5-short.json
mavspy/data/scenes/brick_scene.json
mavspy/data/scenes/cube_scene.json
mavspy/data/scenes/grass_dense.json
mavspy/data/scenes/heightmap_example_scene.json
mavspy/data/scenes/spa_city.json
mavspy/data/scenes/surface_only.json
mavspy/data/scenes/meshes/labels.json
mavspy/data/scenes/meshes/buildings/Apartment_Building_26_obj.mtl
mavspy/data/scenes/meshes/buildings/Apartment_Building_26_obj.obj
mavspy/data/scenes/meshes/buildings/Apartment_Building_6_obj.mtl
mavspy/data/scenes/meshes/buildings/Apartment_Building_6_obj.obj
mavspy/data/scenes/meshes/buildings/Panel_House_Wikipedia_of_Russia_01.mtl
mavspy/data/scenes/meshes/buildings/Panel_House_Wikipedia_of_Russia_01.obj
mavspy/data/scenes/meshes/buildings/Panel_House_Wikipedia_of_Russia_01_01_01_Base_Color.bmp
mavspy/data/scenes/meshes/buildings/Panel_House_Wikipedia_of_Russia_01_01_01_Normal.bmp
mavspy/data/scenes/meshes/buildings/Panel_House_Wikipedia_of_Russia_01_01_02_Base_Color.bmp
mavspy/data/scenes/meshes/buildings/Panel_House_Wikipedia_of_Russia_01_01_02_Normal.bmp
mavspy/data/scenes/meshes/misc/brick.bmp
mavspy/data/scenes/meshes/misc/brick.mtl
mavspy/data/scenes/meshes/misc/brick.obj
mavspy/data/scenes/meshes/misc/cube.mtl
mavspy/data/scenes/meshes/misc/cube.obj
mavspy/data/scenes/meshes/misc/wall.mtl
mavspy/data/scenes/meshes/misc/wall.obj
mavspy/data/scenes/meshes/spectra/agave_leaf.spec
mavspy/data/scenes/meshes/spectra/agave_neck.spec
mavspy/data/scenes/meshes/spectra/aloe_flower.spec
mavspy/data/scenes/meshes/spectra/aloe_leaf.spec
mavspy/data/scenes/meshes/spectra/american_beech_bark.spec
mavspy-1.0.6.dist-info/LICENSE
mavspy-1.0.6.dist-info/METADATA
mavspy-1.0.6.dist-info/WHEEL
mavspy-1.0.6.dist-info/top_level.txt
mavspy-1.0.6.dist-info/RECORD
