Metadata-Version: 2.2
Name: mavspy
Version: 1.0.6
Summary: The MSU Autonomous Vehicle Simulator
Author-email: Chris Goodin <cgoodin@cavs.msstate.edu>
Classifier: Programming Language :: Python :: 3
Classifier: License :: OSI Approved :: MIT License
Classifier: Operating System :: OS Independent
Requires-Python: >=3.8
License-File: LICENSE
Requires-Dist: numpy
